Metadata-Version: 1.0
Name: iseven-aast
Version: 0.0.1
Summary: This is a even-odd checking function.
Home-page: UNKNOWN
Author: Aastha Singh
Author-email: UNKNOWN
License: MIT
Keywords: even,odd,even_odd
Platform: UNKNOWN
